qpmr/__init__.py
qpmr/argument_principle.py
qpmr/distribution.py
qpmr/numerical_methods.py
qpmr/qpmr_v2.py
qpmr/utils.py
qpmr/quasipoly/__init__.py
qpmr/quasipoly/core.py
qpmr-0.0.1.dist-info/LICENSE
qpmr-0.0.1.dist-info/METADATA
qpmr-0.0.1.dist-info/WHEEL
qpmr-0.0.1.dist-info/top_level.txt
qpmr-0.0.1.dist-info/RECORD
