Metadata-Version: 2.1
Name: qpmr
Version: 0.0.1
Summary: Quassi polynomial root finder
Author-email: Adam Peichl <adpeichl@gmail.com>
Maintainer-email: Adam Peichl <adpeichl@gmail.com>
License: GNU GENERAL PUBLIC LICENSE
Project-URL: Homepage, https://github.com/LockeErasmus/qpmr
Project-URL: Repository, https://github.com/LockeErasmus/qpmr
Keywords: timedelay,control,stability,DDE
Classifier: Programming Language :: Python :: 3
Classifier: Development Status :: 4 - Beta
Classifier: License :: OSI Approved :: GNU General Public License v3 (GPLv3)
Classifier: Operating System :: OS Independent
Classifier: Topic :: Scientific/Engineering :: Mathematics
Requires-Python: >=3.10
License-File: LICENSE
Requires-Dist: numpy>=1.24.2
Requires-Dist: scipy>=1.10.1
Requires-Dist: contourpy>=1.0.0
